{
  "_class": "group",
  "do_objectID": "47406746-8508-4331-8909-9DB1C537B489",
  "exportOptions": {
    "_class": "exportOptions",
    "exportFormats": [
    ],
    "includedLayerIds": [
    ],
    "layerOptions": 0,
    "shouldTrim": false
  },
  "frame": {
    "_class": "rect",
    "constrainProportions": false,
    "height": 539,
    "width": 356,
    "x": 0,
    "y": 0
  },
  "hasClickThrough": false,
  "isFlippedHorizontal": false,
  "isFlippedVertical": false,
  "isLocked": false,
  "isVisible": true,
  "layerListExpandedType": 0,
  "layers": [
    {
      "class": "shapeGroup",
      "id": "49B1DBDE-33F1-452E-923C-2FFEA77E5295"
    },
    {
      "class": "bitmap",
      "id": "5FADC7E4-ED11-4A1D-98C1-3552F50038BE"
    },
    {
      "class": "bitmap",
      "id": "8E4126C4-DD80-44C0-B20F-8DA2A5B2B050"
    }
  ],
  "name": "img",
  "nameIsFixed": true,
  "resizingConstraint": 63,
  "resizingType": 0,
  "rotation": 0,
  "shouldBreakMaskChain": false,
  "style": {
    "_class": "style",
    "endDecorationType": 0,
    "miterLimit": 10,
    "startDecorationType": 0
  },
  "userInfo": {
    "com.animaapp.stc-sketch-plugin": {
      "kModelPropertiesKey": {
      }
    }
  }
}